django_sync_package-0.2.0.dist-info/licenses/LICENSE
sync/__init__.py
sync/admin.py
sync/apps.py
sync/models.py
sync/services.py
sync/signals.py
sync/tests.py
sync/views.py
sync/migrations/0001_initial.py
sync/migrations/__init__.py
django_sync_package-0.2.0.dist-info/METADATA
django_sync_package-0.2.0.dist-info/WHEEL
django_sync_package-0.2.0.dist-info/top_level.txt
django_sync_package-0.2.0.dist-info/RECORD
